telemuninn/__init__.py
telemuninn/__main__.py
telemuninn/bot_wrapper.py
telemuninn-0.1.3.dist-info/entry_points.txt
telemuninn-0.1.3.dist-info/LICENSE
telemuninn-0.1.3.dist-info/WHEEL
telemuninn-0.1.3.dist-info/METADATA
telemuninn-0.1.3.dist-info/RECORD
