Metadata-Version: 2.1
Name: telemuninn
Version: 0.1.3
Summary: Just like Alfred but for Telegram
Home-page: https://github.com/namuan/tele-muninn
Author: Namuan
Author-email: me@deskriders.dev
Requires-Python: >=3.7
Classifier: License :: OSI Approved :: MIT License
Classifier: Programming Language :: Python :: 3
